process_wrap_queue/InnerProcessWrap.py
process_wrap_queue/ProcessWrap.py
process_wrap_queue/ProcessWrapQueue.py
process_wrap_queue/__init__.py
process_wrap_queue-0.0.7.dist-info/LICENSE
process_wrap_queue-0.0.7.dist-info/METADATA
process_wrap_queue-0.0.7.dist-info/WHEEL
process_wrap_queue-0.0.7.dist-info/top_level.txt
process_wrap_queue-0.0.7.dist-info/RECORD
