Metadata-Version: 2.1
Name: process_wrap_queue
Version: 0.0.7
Summary: a python module for process based task queue.
Author-email: GGN_2015 <premierbob@qq.com>
License: MIT License
Requires-Python: >=3.11
License-File: LICENSE
